web3_validators/__init__.py
web3_validators-2.1.0.dist-info/LICENSE
web3_validators-2.1.0.dist-info/METADATA
web3_validators-2.1.0.dist-info/WHEEL
web3_validators-2.1.0.dist-info/top_level.txt
web3_validators-2.1.0.dist-info/RECORD
