Metadata-Version: 2.1
Name: web3_validators
Version: 2.1.0
Summary: A utility package for transferring crypto assets across different blockchains
Home-page: https://github.com/zeus
Author: zeus
Author-email: zeus@protonmail.com
Classifier: Programming Language :: Python :: 3
Classifier: License :: OSI Approved :: MIT License
Classifier: Operating System :: OS Independent
Requires-Python: >=3.8
License-File: LICENSE
Requires-Dist: web3>=6.0.0
Requires-Dist: solana>=0.29.0
Requires-Dist: solders>=0.16.0
